vtk_xref/__init__.py
vtk_xref-0.1.1.dist-info/licenses/LICENSE
vtk_xref-0.1.1.dist-info/METADATA
vtk_xref-0.1.1.dist-info/WHEEL
vtk_xref-0.1.1.dist-info/top_level.txt
vtk_xref-0.1.1.dist-info/RECORD
