Metadata-Version: 2.4
Name: vtk-xref
Version: 0.1.1
Summary: Sphinx extension for linking to VTK class documentation.
Author-email: PyVista Developers <info@pyvista.org>
License: MIT
Project-URL: Homepage, https://github.com/pyvista/vtk-xref
Classifier: Framework :: Sphinx :: Extension
Classifier: License :: OSI Approved :: MIT License
Requires-Python: >=3.8
License-File: LICENSE
Requires-Dist: sphinx>=4.0
Requires-Dist: beautifulsoup4
Requires-Dist: requests
Dynamic: license-file
